setup.py
gillcup/__init__.py
gillcup/actions.py
gillcup/animation.py
gillcup/clock.py
gillcup/easing.py
gillcup/effect.py
gillcup/properties.py
gillcup.egg-info/PKG-INFO
gillcup.egg-info/SOURCES.txt
gillcup.egg-info/dependency_links.txt
gillcup.egg-info/requires.txt
gillcup.egg-info/top_level.txt
gillcup/test/__init__.py
gillcup/test/test_action.py
gillcup/test/test_animation.py
gillcup/test/test_clock.py
gillcup/test/test_properties.py