Metadata-Version: 1.0
Name: gillcup
Version: 0.2.0-alpha.0
Summary: An animation framework for Python
Home-page: UNKNOWN
Author: Petr Viktorin
Author-email: encukou@gmail.com
License: UNKNOWN
Platform: UNKNOWN
Classifier: Intended Audience :: Developers
Classifier: License :: OSI Approved :: MIT License
Classifier: Operating System :: OS Independent
Classifier: Programming Language :: Python
Classifier: Programming Language :: Python :: 2
Classifier: Programming Language :: Python :: 2.6
Classifier: Programming Language :: Python :: 2.7
Classifier: Programming Language :: Python :: 3
Classifier: Programming Language :: Python :: 3.1
Classifier: Programming Language :: Python :: 3.2
Classifier: Topic :: Software Development :: Libraries
